odoo9_addon_mgmtsystem_action-9.0.1.0.0.99.dev55-py3.8-nspkg.pth
odoo_addons/mgmtsystem_action/README.rst
odoo_addons/mgmtsystem_action/__init__.py
odoo_addons/mgmtsystem_action/__openerp__.py
odoo_addons/mgmtsystem_action/data/action_sequence.xml
odoo_addons/mgmtsystem_action/data/automated_reminder.xml
odoo_addons/mgmtsystem_action/data/email_template.xml
odoo_addons/mgmtsystem_action/data/mgmtsystem_action_stage.xml
odoo_addons/mgmtsystem_action/demo/mgmtsystem_action.xml
odoo_addons/mgmtsystem_action/i18n/am.po
odoo_addons/mgmtsystem_action/i18n/ar.po
odoo_addons/mgmtsystem_action/i18n/bg.po
odoo_addons/mgmtsystem_action/i18n/bs.po
odoo_addons/mgmtsystem_action/i18n/ca.po
odoo_addons/mgmtsystem_action/i18n/ca_ES.po
odoo_addons/mgmtsystem_action/i18n/cs.po
odoo_addons/mgmtsystem_action/i18n/da.po
odoo_addons/mgmtsystem_action/i18n/da_DK.po
odoo_addons/mgmtsystem_action/i18n/de.po
odoo_addons/mgmtsystem_action/i18n/el_GR.po
odoo_addons/mgmtsystem_action/i18n/en_GB.po
odoo_addons/mgmtsystem_action/i18n/es.po
odoo_addons/mgmtsystem_action/i18n/es_AR.po
odoo_addons/mgmtsystem_action/i18n/es_CL.po
odoo_addons/mgmtsystem_action/i18n/es_CO.po
odoo_addons/mgmtsystem_action/i18n/es_CR.po
odoo_addons/mgmtsystem_action/i18n/es_DO.po
odoo_addons/mgmtsystem_action/i18n/es_EC.po
odoo_addons/mgmtsystem_action/i18n/es_ES.po
odoo_addons/mgmtsystem_action/i18n/es_MX.po
odoo_addons/mgmtsystem_action/i18n/es_PE.po
odoo_addons/mgmtsystem_action/i18n/es_PY.po
odoo_addons/mgmtsystem_action/i18n/es_VE.po
odoo_addons/mgmtsystem_action/i18n/et.po
odoo_addons/mgmtsystem_action/i18n/eu.po
odoo_addons/mgmtsystem_action/i18n/fa.po
odoo_addons/mgmtsystem_action/i18n/fi.po
odoo_addons/mgmtsystem_action/i18n/fr.po
odoo_addons/mgmtsystem_action/i18n/fr_CA.po
odoo_addons/mgmtsystem_action/i18n/fr_CH.po
odoo_addons/mgmtsystem_action/i18n/gl.po
odoo_addons/mgmtsystem_action/i18n/gl_ES.po
odoo_addons/mgmtsystem_action/i18n/he.po
odoo_addons/mgmtsystem_action/i18n/hr.po
odoo9_addon_mgmtsystem_action-9.0.1.0.0.99.dev55.dist-info/METADATA
odoo9_addon_mgmtsystem_action-9.0.1.0.0.99.dev55.dist-info/WHEEL
odoo9_addon_mgmtsystem_action-9.0.1.0.0.99.dev55.dist-info/namespace_packages.txt
odoo9_addon_mgmtsystem_action-9.0.1.0.0.99.dev55.dist-info/top_level.txt
odoo9_addon_mgmtsystem_action-9.0.1.0.0.99.dev55.dist-info/RECORD
